{
  "version": 1,
  "variables": [
    {
      "names": [
        "gamesComMeetupIdLocs",
        "lat",
        "lng"
      ],
      "values": [
        [
          "7519922",
          "30.459",
          "-97.738"
        ],
        [
          "7519923",
          "30.459",
          "-97.736"
        ],
        [
          "7519920",
          "30.457",
          "-97.728"
        ],
        [
          "7519921",
          "30.457",
          "-97.726"
        ],
        [
          "7519926",
          "30.459",
          "-97.73"
        ],
        [
          "7519927",
          "30.459",
          "-97.728"
        ],
        [
          "7519924",
          "30.459",
          "-97.734"
        ],
        [
          "7519925",
          "30.459",
          "-97.732"
        ],
        [
          "7519930",
          "30.461",
          "-97.736"
        ],
        [
          "7519931",
          "30.461",
          "-97.734"
        ],
        [
          "7519928",
          "30.459",
          "-97.726"
        ],
        [
          "7519929",
          "30.461",
          "-97.738"
        ],
        [
          "7519934",
          "30.461",
          "-97.728"
        ],
        [
          "7519935",
          "30.461",
          "-97.726"
        ],
        [
          "7519932",
          "30.461",
          "-97.732"
        ],
        [
          "7519933",
          "30.461",
          "-97.73"
        ],
        [
          "7519915",
          "30.457",
          "-97.738"
        ],
        [
          "7519918",
          "30.457",
          "-97.732"
        ],
        [
          "7519919",
          "30.457",
          "-97.73"
        ],
        [
          "7519916",
          "30.457",
          "-97.736"
        ],
        [
          "7519917",
          "30.457",
          "-97.734"
        ],
        [
          "7519954",
          "30.467",
          "-97.73"
        ],
        [
          "7519955",
          "30.467",
          "-97.728"
        ],
        [
          "7519952",
          "30.467",
          "-97.734"
        ],
        [
          "7519953",
          "30.467",
          "-97.732"
        ],
        [
          "7519958",
          "30.469",
          "-97.736"
        ],
        [
          "7519959",
          "30.469",
          "-97.734"
        ],
        [
          "7519956",
          "30.467",
          "-97.726"
        ],
        [
          "7519957",
          "30.469",
          "-97.738"
        ],
        [
          "7519962",
          "30.469",
          "-97.728"
        ],
        [
          "7519963",
          "30.469",
          "-97.726"
        ],
        [
          "7519960",
          "30.469",
          "-97.732"
        ],
        [
          "7519961",
          "30.469",
          "-97.73"
        ],
        [
          "7519938",
          "30.463",
          "-97.734"
        ],
        [
          "7519939",
          "30.463",
          "-97.732"
        ],
        [
          "7519936",
          "30.463",
          "-97.738"
        ],
        [
          "7519937",
          "30.463",
          "-97.736"
        ],
        [
          "7519942",
          "30.463",
          "-97.726"
        ],
        [
          "7519943",
          "30.465",
          "-97.738"
        ],
        [
          "7519940",
          "30.463",
          "-97.73"
        ],
        [
          "7519941",
          "30.463",
          "-97.728"
        ],
        [
          "7519946",
          "30.465",
          "-97.732"
        ],
        [
          "7519947",
          "30.465",
          "-97.73"
        ],
        [
          "7519944",
          "30.465",
          "-97.736"
        ],
        [
          "7519945",
          "30.465",
          "-97.734"
        ],
        [
          "7519950",
          "30.467",
          "-97.738"
        ],
        [
          "7519951",
          "30.467",
          "-97.736"
        ],
        [
          "7519948",
          "30.465",
          "-97.728"
        ],
        [
          "7519949",
          "30.465",
          "-97.726"
        ]
      ]
    },
    {
      "names": [
        "gamesComMeetupId"
      ],
      "values": [
        [
          "7519939"
        ]
      ]
    },
    {
      "names": [
        "gamesComAnyIdentifiersStart0",
        "gamesComAnyIdentifiersStart1",
        "gamesComAnyIdentifiersStart2",
        "gamesComAnyIdentifiersStart3",
        "gamesComAnyIdentifiersStart4",
        "gamesComAnyIdentifiersStart5",
        "gamesComAnyIdentifiersStart6",
        "gamesComAnyIdentifiersStart7",
        "gamesComAnyIdentifiersStart8",
        "gamesComAnyIdentifiersStart9",
        "gamesComAnyIdentifiersStart10",
        "gamesComAnyIdentifiersStart11",
        "gamesComAnyIdentifiersStart12",
        "gamesComAnyIdentifiersStart13",
        "gamesComAnyIdentifiersStart14",
        "gamesComAnyIdentifiersStart15",
        "gamesComAnyIdentifiersStart16",
        "gamesComAnyIdentifiersStart17",
        "gamesComAnyIdentifiersStart18",
        "gamesComAnyIdentifiersStart19",
        "gamesComAnyIdentifiersEnd",
        "gamesComAnyIdentifiersPrefix",
        "gamesComAnyIdentifiersValue"
      ],
      "values": [
        [
          "0",
          "1",
          "2",
          "3",
          "4",
          "5",
          "6",
          "7",
          "8",
          "9",
          "10",
          "11",
          "12",
          "13",
          "14",
          "15",
          "16",
          "17",
          "18",
          "19",
          "769",
          "GCAnyId",
          "constantAnyIdentifierValue"
        ]
      ]
    },
    {
      "names": [
        "gamesComUserIdStart",
        "gamesComUserIdEnd",
        "gamesComUserIdType"
      ],
      "values": [
        [
          "0",
          "10719",
          "staticUserIdType"
        ]
      ]
    },
    {
      "names": [
        "gamesComOrganizerAccountIdStart",
        "gamesComOrganizerAccountIdEnd",
        "gamesComOrganizerAccountIdPrefix"
      ],
      "values": [
        [
          "20001",
          "20490",
          "GCOrgAccountId"
        ]
      ]
    },
    {
      "names": [
        "worldWideAnyIdentifiersStart",
        "worldWideAnyIdentifiersEnd",
        "worldWideAnyIdentifiersPrefix",
        "worldWideAnyIdentifiersValue"
      ],
      "values": [
        [
          "0",
          "807499",
          "WWAnyId",
          "constantAnyIdentifierValue"
        ]
      ]
    },
    {
      "names": [
        "worldWideOrganizerAccountIdStart",
        "worldWideOrganizerAccountIdEnd",
        "worldWideOrganizerAccountIdPrefix"
      ],
      "values": [
        [
          "1",
          "400000",
          "WWOrgAccountId"
        ]
      ]
    },
    {
      "names": [
        "minutesBeforeVal",
        "minutesAfterVal",
        "gamesComDistanceLimitMetersVal",
        "worldWideDistanceLimitMetersVal"
      ],
      "values": [
        [
          "30",
          "1440",
          "100",
          "100000"
        ]
      ]
    }
  ]
}
